netcord/__init__.py
netcord/_http.py
netcord/cache.py
netcord/config.py
netcord/depends.py
netcord/errors.py
netcord/models.py
netcord/netcord.py
netcord/utils.py
netcord-2.2.5.dist-info/METADATA
netcord-2.2.5.dist-info/WHEEL
netcord-2.2.5.dist-info/licenses/LICENSE
netcord-2.2.5.dist-info/RECORD
