Metadata-Version: 2.4
Name: netcord
Version: 2.2.5
Summary: Asynchronous Discord OAuth2 library for FastAPI (identify, email, guilds scopes support)
Project-URL: HomePage, https://github.com/netrix-team/netcord
Project-URL: GitHub, https://github.com/netrix-team/netcord
Project-URL: Docs, https://netcord.netrix.fun
Author: netrix-team
License: MIT License
License-File: LICENSE
Keywords: api,asyncio,discord,fastapi,netcord,oauth2
Classifier: Development Status :: 4 - Beta
Classifier: Framework :: FastAPI
Classifier: Intended Audience :: Developers
Classifier: License :: OSI Approved :: MIT License
Classifier: Natural Language :: English
Classifier: Programming Language :: Python :: 3
Classifier: Programming Language :: Python :: 3.12
Classifier: Topic :: Internet :: WWW/HTTP :: Session
Classifier: Topic :: Software Development :: Libraries
Requires-Python: >=3.12
Requires-Dist: fastapi>=0.115.12
Requires-Dist: httpx>=0.28.1
Requires-Dist: pydantic>=2.11.4
